modelisation.py
modelisation-1.0.dist-info/METADATA
modelisation-1.0.dist-info/WHEEL
modelisation-1.0.dist-info/top_level.txt
modelisation-1.0.dist-info/RECORD
