Metadata-Version: 2.1
Name: modelisation
Version: 1.0
Summary: Modéliser des points expérimentaux
Home-page: https://urlz.fr/pu0X
Author: LAURENT Stéphane
License: MIT
Keywords: modelisation modélisation physique chimie lycée linéaire affine linear regression physical chemistry modeling
Platform: UNKNOWN
Classifier: Topic :: Education
Requires-Dist: matplotlib (>=3.8.0)
Requires-Dist: numpy (>=1.26.0)
Requires-Dist: scipy (>=1.11.0)
Requires-Dist: addcopyfighandler (>=3.0.0)
